CHANGELOG.txt
LICENSE.txt
MANIFEST.in
README.rst
setup.cfg
setup.py
pogo/__init__.py
pogo/main.py
pogo.egg-info/PKG-INFO
pogo.egg-info/SOURCES.txt
pogo.egg-info/dependency_links.txt
pogo.egg-info/entry_points.txt
pogo.egg-info/requires.txt
pogo.egg-info/top_level.txt
pogo.egg-info/zip-safe
pogo/dao/__init__.py
pogo/dao/local_db_access.py
pogo/dao/record_dao_es.py
pogo/dao/record_dao_local.py
pogo/data/logrotate.cfg
pogo/data/pogo.cfg
pogo/data/pogo_schema.sql
pogo/dto/__init__.py
pogo/dto/record.py
pogo/file/__init__.py
pogo/file/file_lister.py
pogo/file/stretch_file.py
pogo/service/__init__.py
pogo/service/service_local.py
pogo/util/__init__.py
pogo/util/config.py
pogo/util/util.py