Metadata-Version: 1.1
Name: pogo
Version: 0.9.3.7
Summary: Pogo is a utility for putting data generated by a HonSSH honeypot into an Elasticsearch database.
Home-page: https://github.com/tonyrein/pogo.git
Author: Tony Rein
Author-email: boing.to.elasticsearch@gmail.com
License: MIT
Keywords: HonSSH Elasticsearch Python Honeypot cybersecurity
Platform: UNKNOWN
Classifier: Development Status :: 4 - Beta
Classifier: Environment :: Console
Classifier: Operating System :: POSIX :: Linux
Classifier: Programming Language :: Python
Classifier: License :: OSI Approved :: MIT License
Classifier: Natural Language :: English
Classifier: Topic :: Security
Classifier: Topic :: Utilities
Classifier: Intended Audience :: System Administrators
